_black_version.py
black/__init__.py
black/__main__.py
black/py.typed
black_primer/cli.py
black_primer/lib.py
blackd/__init__.py
blib2to3/Grammar.txt
blib2to3/PatternGrammar.txt
blib2to3/__init__.py
blib2to3/pygram.py
blib2to3/pytree.py
blib2to3/pgen2/__init__.py
blib2to3/pgen2/conv.py
blib2to3/pgen2/driver.py
blib2to3/pgen2/grammar.py
blib2to3/pgen2/literals.py
blib2to3/pgen2/parse.py
blib2to3/pgen2/pgen.py
blib2to3/pgen2/token.py
blib2to3/pgen2/tokenize.py
blacksin-20.8b1.post0.dist-info/LICENSE
blacksin-20.8b1.post0.dist-info/METADATA
blacksin-20.8b1.post0.dist-info/WHEEL
blacksin-20.8b1.post0.dist-info/entry_points.txt
blacksin-20.8b1.post0.dist-info/top_level.txt
blacksin-20.8b1.post0.dist-info/RECORD
